{
    "teacher": [
        {
        "id":1244,
        "name":"Manju",
        "password":"12345678",
        "admin":false
    },
    {
        "id":1234,
        "name":"Keertena",
        "password":"87654321",
        "admin":true
    },
    {
        "id":2345,
        "name":"Shibu",
        "password":"password",
        "admin":true
    }
  ],
  "teachers": [
    {
      "id": "1244",
      "user_name": "Manju",
      "subject": "Programming In Python",
      "stream": "CS",
      "img_data": "assets/test.jpeg"
    },
    {
      "id": "1234",
      "user_name": "Keertena",
      "subject": "Computer Network",
      "stream": "CS",
      "img_data": "assets/test.jpeg"
    },
    {
      "id": "2345",
      "user_name": "Shibu",
      "subject": "Compiler",
      "stream": "CS",
      "img_data": "assets/test.jpeg"
    }
  ],
  "studentsData": [
    {
      "id": "9155CS20",
      "user_name": "Imtiyaz-Ali",
      "roll": 27,
      "stream": "CS",
      "img_data": "assets/students/me.jpeg"
    },
    {
      "id": "9028CS20",
      "user_name": "Kashinath S",
      "roll": 30,
      "stream": "CS",
      "img_data": "assets/students/kashi.jpg"
    },
    {
      "id": "8842CS20",
      "user_name": "Govind P",
      "roll": 26,
      "stream": "CS",
      "img_data": "assets/students/govind.jpg"
    },
    {
      "id": "9094CS20",
      "user_name": "AlanSavio",
      "roll": 7,
      "stream": "CS",
      "img_data": "assets/students/savio.jpg"
    }
  ],
  "students": [
    {
      "id": 1,
      "1": [
        false,
        [
          "42",
          "58"
        ],
        [
          "10",
          "41",
          "3",
          "59"
        ],
        [
          "57",
          "32",
          "54"
        ],
        [
          "32",
          "17",
          "5"
        ],
        [
          "32",
          "3",
          "45"
        ],
        false,
        false,
        [
          "29",
          "7",
          "23"
        ],
        [
          "58",
          "6",
          "41",
          "10",
          "42"
        ],
        [
          "26",
          "37",
          "35",
          "3"
        ],
        [
          "60",
          "30",
          "52",
          "30"
        ],
        [
          "58",
          "10"
        ],
        false,
        false,
        [
          "5",
          "19"
        ],
        [
          "52"
        ],
        [
          "2",
          "52",
          "29",
          "11",
          "8"
        ],
        [
          "57",
          "42"
        ],
        [
          "15",
          "52",
          "3"
        ],
        false,
        false,
        [
          "46",
          "54",
          "59"
        ],
        [
          "1"
        ],
        [
          "18",
          "28",
          "52",
          "48",
          "48"
        ],
        [
          "40",
          "7",
          "28",
          "16",
          "47"
        ],
        [
          "16",
          "14",
          "31",
          "12"
        ],
        false,
        false,
        [
          "27",
          "3",
          "8"
        ],
        [
          "45"
        ]
      ]
    },
    {
      "id": 2,
      "2": [
        ["38"],
        ["23"],
        ["55","10","24","25"],
        false,
        false,
        ["59","57","18"],
        ["27","59"],
        ["27","39","44","42",
          "33"
        ],
        [
          "30",
          "10",
          "33",
          "23",
          "49"
        ],
        [
          "45"
        ],
        false,
        false,
        [
          "4"
        ],
        [
          "16"
        ],
        [
          "36",
          "22"
        ],
        [
          "28",
          "32",
          "38"
        ],
        [
          "11",
          "60",
          "55"
        ],
        false,
        false,
        [
          "30",
          "24",
          "43",
          "42"
        ],
        [
          "48",
          "39",
          "10",
          "11",
          "28"
        ],
        [
          "50"
        ],
        [
          "15",
          "11",
          "43"
        ],
        [
          "50",
          "43",
          "39",
          "6",
          "40"
        ],
        false,
        false,
        [
          "37",
          "22",
          "6",
          "15",
          "34"
        ],
        [
          "14",
          "45",
          "28",
          "49"
        ]
      ]
    },
    {
      "id": 3,
      "3": [
        [
          "29",
          "50",
          "2",
          "32"
        ],
        [
          "41",
          "57"
        ],
        [
          "5"
        ],
        false,
        false,
        [
          "32",
          "54",
          "5",
          "14",
          "42"
        ],
        [
          "14",
          "12"
        ],
        [
          "41",
          "34",
          "58",
          "19"
        ],
        [
          "47"
        ],
        [
          "43",
          "41",
          "7",
          "14",
          "58"
        ],
        false,
        false,
        [
          "55",
          "51",
          "47"
        ],
        [
          "55"
        ],
        [
          "2",
          "3",
          "48",
          "39",
          "11"
        ],
        [
          "22",
          "57"
        ],
        [
          "20"
        ],
        false,
        false,
        [
          "35",
          "8",
          "22",
          "7"
        ],
        [
          "42",
          "60",
          "47"
        ],
        [
          "17",
          "53"
        ],
        [
          "49"
        ],
        [
          "4"
        ],
        false,
        false,
        [
          "1",
          "36",
          "48",
          "58",
          "24"
        ],
        [
          "17",
          "2",
          "5",
          "2"
        ],
        [
          "22"
        ],
        [
          "13"
        ],
        [
          "48",
          "52",
          "18",
          "54",
          "28"
        ]
      ]
    },
    {
  "id": 4,
  "4": [
    false,
    false,
    ["55"],
    ["40", "57", "39", "45"],
    ["29", "1", "1", "53", "3"],
    ["43", "4"],
    ["27"],
    false,
    false,
    ["24", "3", "30", "6", "3"],
    ["55"],
    ["60", "38"],
    ["9", "19", "26", "5", "11"],
    ["3", "39", "50", "23", "23"],
    false,
    false,
    ["54", "38", "41", "6"],
    ["26", "38", "4", "34", "52"],
    ["33", "21"],
    ["20", "59", "58"],
    ["42", "26", "33", "10", "4"],
    false,
    false,
    ["47", "29", "24", "42"],
    ["8", "50"],
    ["40"],
    ["12", "51", "19", "8"],
    [ "37" ],
    false,
    false
  ]
},
{
  "id": 5,
  "5": [
    false,
    false,
    false,
    false,
    false,
    false,
    false,
    false,
    false,
    false,
    false,
    false,
    false,
    false,
    false,
    false,
    false,
    false,
    false,
    false,
    false,
    false,
    false,
    false,
    false,
    false,
    false,
    false,
    false,
    false,
    false
  ]
},
{
  "id": 6,
  "6": [
    [
      "23",
      "22"
    ],
    [
      "17",
      "41",
      "59",
      "4",
      "24"
    ],
    false,
    false,
    [
      "44",
      "38"
    ],
    [
      "20",
      "59",
      "54",
      "9",
      "41"
    ],
    [
      "53",
      "36",
      "28",
      "40"
    ],
    [
      "49",
      "53"
    ],
    [
      "10",
      "35",
      "40"
    ],
    false,
    false,
    [
      "42",
      "31"
    ],
    [
      "35"
    ],
    [
      "47"
    ],
    [
      "45"
    ],
    [
      "36",
      "4",
      "40",
      "44",
      "21"
    ],
    false,
    false,
    [
      "20"
    ],
    [
      "58",
      "26",
      "49",
      "43",
      "42"
    ],
    [
      "14",
      "22"
    ],
    [
      "46",
      "8",
      "19",
      "26",
      "40"
    ],
    [
      "5",
      "28"
    ],
    false,
    false,
    [
      "56"
    ],
    [
      "45"
    ],
    [
      "6",
      "29",
      "48",
      "8"
    ],
    [
      "44",
      "57",
      "36",
      "24"
    ],
    [
      "51",
      "14"
    ]
  ]
},
{
  "id": 7,
  "7": [
    false,
    false,
    [
      "53",
      "57",
      "48",
      "53"
    ],
    [
      "33",
      "55",
      "29",
      "21",
      "14"
    ],
    [
      "12",
      "41",
      "31"
    ],
    [
      "14",
      "50",
      "58"
    ],
    [
      "4",
      "36",
      "15"
    ],
    false,
    false,
    [
      "52",
      "24"
    ],
    [
      "49",
      "28",
      "2",
      "12",
      "1"
    ],
    [
      "26",
      "52"
    ],
    [
      "2"
    ],
    [
      "25",
      "2",
      "38",
      "29"
    ],
    false,
    false,
    [
      "13",
      "48"
    ],
    [
      "8",
      "13",
      "52",
      "11",
      "25"
    ],
    [
      "52",
      "24",
      "19",
      "51",
      "45"
    ],
    [
      "60",
      "16",
      "43",
      "59"
    ],
    [
      "22",
      "17",
      "24",
      "17",
      "23"
    ],
    false,
    false,
    [
      "51",
      "3"
    ],
    [
      "25",
      "21",
      "7"
    ],
    [
      "23",
      "12",
      "3",
      "13"
    ],
    [
      "43",
      "37",
      "45"
    ],
    [
      "24",
      "47",
      "26"
    ],
    false,
    false,
    [
      "45",
      "21",
      "41",
      "5",
      "8"
    ]
  ]
}

  ]
}